[
  {
    "title": "The Nico Experience",
    "description": "This is a power fantasy list with emphasis on Immersion, Details, LOD, Parallax textures, higher poly models, MCO combat, and Survival featuring new creatures, new worldspaces, stunning visuals, lighting, weather, and fast paced fun game play.",
    "author": "nicoroshi",
    "maintainers": [
      "github/therealnicoroshi"
    ],
    "game": "skyrimspecialedition",
    "official": false,
    "tags": [
      "Fantasy",
      "MCO",
      "New Worldspaces",
      "Graphics",
      "New Creatures",
      "New Quests"
    ],
    "nsfw": false,
    "utility_list": false,
    "image_contains_title": true,
    "DisplayVersionOnlyInInstallerView": false,
    "force_down": false,
    "links": {
      "image": "https://raw.githubusercontent.com/therealnicoroshi/modlist/main/NewCoverArtNE.jpg",
      "readme": "https://github.com/therealnicoroshi/modlist/blob/main/README.md",
      "download": "https://authored-files.wabbajack.org/The Nico Experience.wabbajack_83f70a5a-5cfd-4600-8a5b-7ecabf55814f",
      "machineURL": "The_Nico_Experience",
      "discordURL": "https://discord.gg/kHehbzuFZ4"
    },
    "download_metadata": {
      "Hash": "V0e1xu7e3+c=",
      "Size": 1248103063,
      "NumberOfArchives": 1711,
      "SizeOfArchives": 157182505973,
      "NumberOfInstalledFiles": 517774,
      "SizeOfInstalledFiles": 304554566704
    },
    "version": "1.4.0",
    "dateCreated": "1970-01-01T00:00:00Z",
    "dateUpdated": "2024-04-11T06:59:50.975108Z",
    "repositoryName": ""
  }
]